textual_transitions/__init__.py
textual_transitions/blinds.py
textual_transitions/curtain.py
textual_transitions/drapes.py
textual_transitions/fire.py
textual_transitions/iris.py
textual_transitions/matrix.py
textual_transitions/mixins.py
textual_transitions/scanline.py
textual_transitions/water.py
textual_transitions-0.0.3.dist-info/licenses/LICENSE
textual_transitions-0.0.3.dist-info/METADATA
textual_transitions-0.0.3.dist-info/WHEEL
textual_transitions-0.0.3.dist-info/top_level.txt
textual_transitions-0.0.3.dist-info/RECORD
