Metadata-Version: 2.4
Name: textual-transitions
Version: 0.0.3
Summary: Transition effects for Textual TUI apps
Author-email: Christopher Trudeau <ctrudeau+pypi@arsensa.com>
License: MIT License
Project-URL: repository, https://github.com/cltrudeau/textual-transitions
Project-URL: documentation, https://textual-transitions.readthedocs.io/en/latest/index.html
Classifier: Development Status :: 3 - Alpha
Classifier: Environment :: Console
Classifier: Intended Audience :: Developers
Classifier: License :: OSI Approved :: MIT License
Classifier: Operating System :: OS Independent
Classifier: Programming Language :: Python :: 3.13
Classifier: Topic :: Software Development :: Libraries :: Python Modules
License-File: LICENSE
Requires-Dist: textual>=5.3
Provides-Extra: build
Requires-Dist: build~=1.3; extra == "build"
Requires-Dist: twine~=6.2; extra == "build"
Provides-Extra: dev
Requires-Dist: pyflakes==3.4.0; extra == "dev"
Requires-Dist: Sphinx==8.2.3; extra == "dev"
Requires-Dist: sphinx-rtd-theme==3.0.2; extra == "dev"
Requires-Dist: textual-dev==1.7.0; extra == "dev"
Requires-Dist: waelstow~=0.12; extra == "dev"
Dynamic: license-file
